lawdocx/__init__.py
lawdocx/audit.py
lawdocx/boilerplate.py
lawdocx/brackets.py
lawdocx/changes.py
lawdocx/cli.py
lawdocx/comments.py
lawdocx/footnotes.py
lawdocx/highlights.py
lawdocx/io_utils.py
lawdocx/metadata.py
lawdocx/models.py
lawdocx/outline.py
lawdocx/todos.py
lawdocx/utils.py
lawdocx-0.2.0.dist-info/METADATA
lawdocx-0.2.0.dist-info/WHEEL
lawdocx-0.2.0.dist-info/entry_points.txt
lawdocx-0.2.0.dist-info/licenses/LICENSE
lawdocx-0.2.0.dist-info/RECORD
