Metadata-Version: 2.4
Name: lawdocx
Version: 0.2.0
Summary: Little tools for dealing with docx files, useful for lawyers and their LLMs
Project-URL: Repository, https://github.com/splittist/lawdocx
Author: John Q Splittist
License-Expression: Apache-2.0
License-File: LICENSE
Classifier: Development Status :: 4 - Beta
Classifier: Programming Language :: Python
Requires-Python: >=3.9
Requires-Dist: click>=8.1.0
Requires-Dist: docx2python>=2.0.0
Requires-Dist: lxml>=4.9.0
